quillsafe/__init__.py
quillsafe/apps.py
quillsafe/fields.py
quillsafe/sample_project/articles/__init__.py
quillsafe/sample_project/articles/admin.py
quillsafe/sample_project/articles/apps.py
quillsafe/sample_project/articles/forms.py
quillsafe/sample_project/articles/migrations/0001_initial.py
quillsafe/sample_project/articles/migrations/__init__.py
quillsafe/sample_project/articles/models.py
quillsafe/sample_project/articles/templates/articles/article_detail.html
quillsafe/sample_project/articles/templates/articles/article_form.html
quillsafe/sample_project/articles/templates/articles/article_list.html
quillsafe/sample_project/articles/tests.py
quillsafe/sample_project/articles/urls.py
quillsafe/sample_project/articles/views.py
quillsafe/sample_project/manage.py
quillsafe/sample_project/sample_project/__init__.py
quillsafe/sample_project/sample_project/asgi.py
quillsafe/sample_project/sample_project/settings.py
quillsafe/sample_project/sample_project/urls.py
quillsafe/sample_project/sample_project/wsgi.py
quillsafe/sample_project/scripts/run.sh
quillsafe/static/quillsafe/quill.js
quillsafe/static/quillsafe/quill.min.js
quillsafe/static/quillsafe/quill.snow.css
quillsafe/static/quillsafe/quill.snow.min.css
quillsafe/templatetags/__init__.py
quillsafe/templatetags/quill_tags.py
quillsafe/widgets.py
django_quill_safe-0.1.3.dist-info/LICENSE
django_quill_safe-0.1.3.dist-info/METADATA
django_quill_safe-0.1.3.dist-info/WHEEL
django_quill_safe-0.1.3.dist-info/entry_points.txt
django_quill_safe-0.1.3.dist-info/RECORD
