Metadata-Version: 2.3
Name: django-quill-safe
Version: 0.1.3
Summary: Safe and minimal integration of Quill editor in Django using JSON delta format only.
License: MIT
Author: Abhilash Ramachandran
Author-email: abhilash.sixthsense@gmail.com
Requires-Python: >=3.11,<4.0
Classifier: License :: OSI Approved :: MIT License
Classifier: Programming Language :: Python :: 3
Classifier: Programming Language :: Python :: 3.11
Classifier: Programming Language :: Python :: 3.12
Classifier: Programming Language :: Python :: 3.13
Requires-Dist: Django (>=5,<6)
